pylightcurve_torch/__init__.py
pylightcurve_torch/_constants.py
pylightcurve_torch/functional.py
pylightcurve_torch/nn.py
pylightcurve_torch-1.1.0.dist-info/LICENSE
pylightcurve_torch-1.1.0.dist-info/METADATA
pylightcurve_torch-1.1.0.dist-info/WHEEL
pylightcurve_torch-1.1.0.dist-info/top_level.txt
pylightcurve_torch-1.1.0.dist-info/RECORD
