Metadata-Version: 2.1
Name: pylightcurve-torch
Version: 1.1.0
Summary: Transit modelling in Pytorch
Home-page: https://github.com/ucl-exoplanets/pylightcurve-torch.git
Author: Mario Morvan
Author-email: mario.morvan.18@ucl.ac.uk
License: UNKNOWN
Platform: UNKNOWN
Classifier: License :: OSI Approved :: GNU General Public License (GPL)
Classifier: Programming Language :: Python :: 3
Classifier: Programming Language :: Python :: 3.6
Classifier: Programming Language :: Python :: 3.7
Classifier: Programming Language :: Python :: 3.8
Classifier: Operating System :: OS Independent
Requires-Python: >=3.6
Requires-Dist: torch
